Metadata-Version: 2.1
Name: example-app-kc-yelmi
Version: 0.0.20
Summary: A small example package
Author: Yelmi Almonte
Author-email: yelmialmonte@gmail.com
Requires-Python: >=3.9
Requires-Dist: coloredlogs
